{
  "main": {
    "id": "716c1dd16fb6765b",
    "type": "split",
    "children": [
      {
        "id": "f3e3bc3430a3aa7a",
        "type": "tabs",
        "children": [
          {
            "id": "e75520d4b1e96ef9",
            "type": "leaf",
            "state": {
              "type": "empty",
              "state": {},
              "icon": "lucide-file",
              "title": "New tab"
            }
          }
        ]
      }
    ],
    "direction": "vertical"
  },
  "left": {
    "id": "673ab7dd183ccc79",
    "type": "split",
    "children": [
      {
        "id": "58c10cb4e3835073",
        "type": "tabs",
        "children": [
          {
            "id": "7f38d16e940af8a8",
            "type": "leaf",
            "state": {
              "type": "file-explorer",
              "state": {
                "sortOrder": "alphabetical",
                "autoReveal": false
              },
              "icon": "lucide-folder-closed",
              "title": "Files"
            }
          },
          {
            "id": "1888dba9cc7d5975",
            "type": "leaf",
            "state": {
              "type": "search",
              "state": {
                "query": "",
                "matchingCase": false,
                "explainSearch": false,
                "collapseAll": false,
                "extraContext": false,
                "sortOrder": "alphabetical"
              },
              "icon": "lucide-search",
              "title": "Search"
            }
          }
        ]
      }
    ],
    "direction": "horizontal",
    "width": 317.5
  },
  "right": {
    "id": "9f20626e890cc6df",
    "type": "split",
    "children": [
      {
        "id": "25ddc37371ada543",
        "type": "tabs",
        "dimension": 57.8883495145631,
        "children": [
          {
            "id": "e35d830992aa79d9",
            "type": "leaf",
            "state": {
              "type": "bookmarks",
              "state": {},
              "icon": "lucide-bookmark",
              "title": "Bookmarks"
            }
          },
          {
            "id": "8e314c23f5189f5c",
            "type": "leaf",
            "state": {
              "type": "outline",
              "state": {
                "file": "assembly.md"
              },
              "icon": "lucide-list",
              "title": "Outline of assembly"
            }
          }
        ]
      },
      {
        "id": "84c4bec7b73427bd",
        "type": "tabs",
        "dimension": 42.1116504854369,
        "children": [
          {
            "id": "d2317c6938837535",
            "type": "leaf",
            "state": {
              "type": "outgoing-link",
              "state": {
                "file": "assembly.md",
                "linksCollapsed": false,
                "unlinkedCollapsed": true
              },
              "icon": "links-going-out",
              "title": "Outgoing links from assembly"
            }
          },
          {
            "id": "50b0303b32ae288c",
            "type": "leaf",
            "state": {
              "type": "backlink",
              "state": {
                "file": "assembly.md",
                "collapseAll": false,
                "extraContext": false,
                "sortOrder": "alphabetical",
                "showSearch": false,
                "searchQuery": "",
                "backlinkCollapsed": false,
                "unlinkedCollapsed": false
              },
              "icon": "links-coming-in",
              "title": "Backlinks for assembly"
            }
          },
          {
            "id": "605e602599165248",
            "type": "leaf",
            "state": {
              "type": "tag",
              "state": {
                "sortOrder": "frequency",
                "useHierarchy": false
              },
              "icon": "lucide-tags",
              "title": "Tags"
            }
          }
        ]
      }
    ],
    "direction": "horizontal",
    "width": 222.5,
    "collapsed": true
  },
  "left-ribbon": {
    "hiddenItems": {
      "switcher:Open quick switcher": false,
      "graph:Open graph view": false,
      "canvas:Create new canvas": false,
      "daily-notes:Open today's daily note": false,
      "templates:Insert template": false,
      "command-palette:Open command palette": false
    }
  },
  "floating": {
    "id": "8e32f730e2065b12",
    "type": "floating",
    "children": [
      {
        "id": "66441d55d81a95cf",
        "type": "window",
        "children": [
          {
            "id": "ad911293e26e872a",
            "type": "tabs",
            "children": [
              {
                "id": "0d68acc725ee1a21",
                "type": "leaf",
                "state": {
                  "type": "pdf",
                  "state": {
                    "file": "doc/atmega328p.pdf"
                  },
                  "icon": "lucide-file-text",
                  "title": "atmega328p"
                }
              }
            ]
          }
        ],
        "direction": "vertical",
        "x": 1507,
        "y": 108,
        "width": 1177,
        "height": 784,
        "maximize": true,
        "zoom": 0
      }
    ]
  },
  "active": "e75520d4b1e96ef9",
  "lastOpenFiles": [
    "assembly/AVR-architecture.md",
    "lib.md",
    "doc/atmega328p.pdf",
    "about_code.md",
    "directives.md",
    "env-info.md",
    "makefiles.md",
    "tree.md",
    "doc/AVR-IS.pdf",
    "doc/AVR-Assembler.pdf",
    "Untitled",
    "doc/GCC-as.pdf",
    "IS-table.md",
    "assembly",
    "2025-01-25.md",
    "Untitled.canvas"
  ]
}